{
  "label": "Guides",
  "position": 4,
  "collapsed": false,
  "link": {
    "type": "generated-index",
    "description": "Variety of guides and tutorials on various IT and server topics. These guides are intended for IT professionals who need to manage and maintain their systems and servers. They cover topics such as system administration, networking installation and configuration, security policies and procedures, data privacy, and much more. If you are in the IT industry and looking for guides to help you manage your systems and servers, this is the place to start."
  }
}
